xbmcjson/__init__.py
xbmcjson/xbmcjson.py
xbmc_json-0.3.2.dist-info/WHEEL
xbmc_json-0.3.2.dist-info/top_level.txt
xbmc_json-0.3.2.dist-info/METADATA
xbmc_json-0.3.2.dist-info/metadata.json
xbmc_json-0.3.2.dist-info/RECORD
xbmc_json-0.3.2.dist-info/DESCRIPTION.rst
